[
  {
    "direction": "Flat", 
    "trend": 4, 
    "dateString": "2016-02-12T12:49:49.000Z", 
    "sgv": 92, 
    "device": "share2", 
    "date": 1455281389000, 
    "_id": "56bdd54337663704c846fd4e", 
    "type": "sgv"
  }, 
  {
    "direction": "Flat", 
    "trend": 4, 
    "dateString": "2016-02-12T12:44:49.000Z", 
    "sgv": 93, 
    "device": "share2", 
    "date": 1455281089000, 
    "_id": "56bdd41737663704c846fd42", 
    "type": "sgv"
  }, 
  {
    "direction": "Flat", 
    "trend": 4, 
    "dateString": "2016-02-12T12:39:49.000Z", 
    "sgv": 93, 
    "device": "share2", 
    "date": 1455280789000, 
    "_id": "56bdd2eb37663704c846fd33", 
    "type": "sgv"
  }, 
  {
    "direction": "Flat", 
    "trend": 4, 
    "dateString": "2016-02-12T12:34:49.000Z", 
    "sgv": 93, 
    "device": "share2", 
    "date": 1455280489000, 
    "_id": "56bdd1bf37663704c846fd23", 
    "type": "sgv"
  }, 
  {
    "direction": "Flat", 
    "trend": 4, 
    "dateString": "2016-02-12T12:29:49.000Z", 
    "sgv": 96, 
    "device": "share2", 
    "date": 1455280189000, 
    "_id": "56bdd09337663704c846fd17", 
    "type": "sgv"
  }, 
  {
    "direction": "Flat", 
    "trend": 4, 
    "dateString": "2016-02-12T12:24:49.000Z", 
    "sgv": 98, 
    "device": "share2", 
    "date": 1455279889000, 
    "_id": "56bdcf6737663704c846fd08", 
    "type": "sgv"
  }, 
  {
    "direction": "Flat", 
    "trend": 4, 
    "dateString": "2016-02-12T12:19:49.000Z", 
    "sgv": 101, 
    "device": "share2", 
    "date": 1455279589000, 
    "_id": "56bdce3b37663704c846fcfd", 
    "type": "sgv"
  }, 
  {
    "direction": "Flat", 
    "trend": 4, 
    "dateString": "2016-02-12T12:14:49.000Z", 
    "sgv": 101, 
    "device": "share2", 
    "date": 1455279289000, 
    "_id": "56bdcd0f37663704c846fcf1", 
    "type": "sgv"
  }, 
  {
    "direction": "Flat", 
    "trend": 4, 
    "dateString": "2016-02-12T12:09:49.000Z", 
    "sgv": 101, 
    "device": "share2", 
    "date": 1455278989000, 
    "_id": "56bdcbe337663704c846fce6", 
    "type": "sgv"
  }, 
  {
    "direction": "Flat", 
    "trend": 4, 
    "dateString": "2016-02-12T12:04:50.000Z", 
    "sgv": 101, 
    "device": "share2", 
    "date": 1455278690000, 
    "_id": "56bdcab737663704c846fcda", 
    "type": "sgv"
  }
]