[
  {
    "direction": "Flat", 
    "trend": 4, 
    "dateString": "2016-02-12T00:44:50.000Z", 
    "sgv": 180, 
    "device": "share2", 
    "date": 1455237890000, 
    "_id": "56bd2b2537663704c846f5e6", 
    "type": "sgv"
  }, 
  {
    "direction": "Flat", 
    "trend": 4, 
    "dateString": "2016-02-12T00:39:50.000Z", 
    "sgv": 177, 
    "device": "share2", 
    "date": 1455237590000, 
    "_id": "56bd29f937663704c846f5d8", 
    "type": "sgv"
  }, 
  {
    "direction": "Flat", 
    "trend": 4, 
    "dateString": "2016-02-12T00:34:50.000Z", 
    "sgv": 176, 
    "device": "share2", 
    "date": 1455237290000, 
    "_id": "56bd28cd37663704c846f5ce", 
    "type": "sgv"
  }, 
  {
    "direction": "Flat", 
    "trend": 4, 
    "dateString": "2016-02-12T00:29:50.000Z", 
    "sgv": 175, 
    "device": "share2", 
    "date": 1455236990000, 
    "_id": "56bd27a137663704c846f5c1", 
    "type": "sgv"
  }, 
  {
    "direction": "Flat", 
    "trend": 4, 
    "dateString": "2016-02-12T00:24:51.000Z", 
    "sgv": 173, 
    "device": "share2", 
    "date": 1455236691000, 
    "_id": "56bd267537663704c846f5b5", 
    "type": "sgv"
  }, 
  {
    "direction": "Flat", 
    "trend": 4, 
    "dateString": "2016-02-12T00:19:51.000Z", 
    "sgv": 173, 
    "device": "share2", 
    "date": 1455236391000, 
    "_id": "56bd254a37663704c846f5a6", 
    "type": "sgv"
  }, 
  {
    "direction": "Flat", 
    "trend": 4, 
    "dateString": "2016-02-12T00:14:51.000Z", 
    "sgv": 172, 
    "device": "share2", 
    "date": 1455236091000, 
    "_id": "56bd241d37663704c846f599", 
    "type": "sgv"
  }, 
  {
    "direction": "Flat", 
    "trend": 4, 
    "dateString": "2016-02-12T00:09:50.000Z", 
    "sgv": 171, 
    "device": "share2", 
    "date": 1455235790000, 
    "_id": "56bd22f137663704c846f58e", 
    "type": "sgv"
  }, 
  {
    "direction": "Flat", 
    "trend": 4, 
    "dateString": "2016-02-12T00:04:51.000Z", 
    "sgv": 166, 
    "device": "share2", 
    "date": 1455235491000, 
    "_id": "56bd21c437663704c846f582", 
    "type": "sgv"
  }, 
  {
    "direction": "FortyFiveUp", 
    "trend": 3, 
    "dateString": "2016-02-11T23:59:51.000Z", 
    "sgv": 167, 
    "device": "share2", 
    "date": 1455235191000, 
    "_id": "56bd20a937663704c846f574", 
    "type": "sgv"
  }
]