[
  {
    "direction": "Flat", 
    "trend": 4, 
    "dateString": "2016-02-02T17:00:12.000Z", 
    "sgv": 113, 
    "device": "share2", 
    "date": 1454432412000, 
    "_id": "56b0e12537663704c8466f74", 
    "type": "sgv"
  }, 
  {
    "direction": "Flat", 
    "trend": 4, 
    "dateString": "2016-02-02T16:55:13.000Z", 
    "sgv": 110, 
    "device": "share2", 
    "date": 1454432113000, 
    "_id": "56b0dff937663704c8466f68", 
    "type": "sgv"
  }, 
  {
    "direction": "Flat", 
    "trend": 4, 
    "dateString": "2016-02-02T16:50:12.000Z", 
    "sgv": 109, 
    "device": "share2", 
    "date": 1454431812000, 
    "_id": "56b0decd37663704c8466f60", 
    "type": "sgv"
  }, 
  {
    "direction": "Flat", 
    "trend": 4, 
    "dateString": "2016-02-02T16:45:13.000Z", 
    "sgv": 109, 
    "device": "share2", 
    "date": 1454431513000, 
    "_id": "56b0dda137663704c8466f57", 
    "type": "sgv"
  }, 
  {
    "direction": "Flat", 
    "trend": 4, 
    "dateString": "2016-02-02T16:40:15.000Z", 
    "sgv": 109, 
    "device": "share2", 
    "date": 1454431215000, 
    "_id": "56b0dc7537663704c8466f4d", 
    "type": "sgv"
  }, 
  {
    "direction": "Flat", 
    "trend": 4, 
    "dateString": "2016-02-02T16:35:13.000Z", 
    "sgv": 106, 
    "device": "share2", 
    "date": 1454430913000, 
    "_id": "56b0db4a37663704c8466f43", 
    "type": "sgv"
  }, 
  {
    "direction": "Flat", 
    "trend": 4, 
    "dateString": "2016-02-02T16:30:13.000Z", 
    "sgv": 105, 
    "device": "share2", 
    "date": 1454430613000, 
    "_id": "56b0da1d37663704c8466f38", 
    "type": "sgv"
  }, 
  {
    "direction": "Flat", 
    "trend": 4, 
    "dateString": "2016-02-02T16:25:12.000Z", 
    "sgv": 105, 
    "device": "share2", 
    "date": 1454430312000, 
    "_id": "56b0d8f137663704c8466f2b", 
    "type": "sgv"
  }, 
  {
    "direction": "Flat", 
    "trend": 4, 
    "dateString": "2016-02-02T16:20:15.000Z", 
    "sgv": 105, 
    "device": "share2", 
    "date": 1454430015000, 
    "_id": "56b0d7c537663704c8466f21", 
    "type": "sgv"
  }, 
  {
    "direction": "Flat", 
    "trend": 4, 
    "dateString": "2016-02-02T16:15:13.000Z", 
    "sgv": 105, 
    "device": "share2", 
    "date": 1454429713000, 
    "_id": "56b0d69a37663704c8466f17", 
    "type": "sgv"
  }
]