[
  {
    "direction": "Flat", 
    "trend": 4, 
    "dateString": "2016-01-26T05:35:30.000Z", 
    "sgv": 151, 
    "device": "share2", 
    "date": 1453786530000, 
    "_id": "56a705ec37663704c8460334", 
    "type": "sgv"
  }, 
  {
    "direction": "Flat", 
    "trend": 4, 
    "dateString": "2016-01-26T05:30:31.000Z", 
    "sgv": 155, 
    "device": "share2", 
    "date": 1453786231000, 
    "_id": "56a704c037663704c8460326", 
    "type": "sgv"
  }, 
  {
    "direction": "Flat", 
    "trend": 4, 
    "dateString": "2016-01-26T05:25:31.000Z", 
    "sgv": 159, 
    "device": "share2", 
    "date": 1453785931000, 
    "_id": "56a7039437663704c8460315", 
    "type": "sgv"
  }, 
  {
    "direction": "Flat", 
    "trend": 4, 
    "dateString": "2016-01-26T05:20:31.000Z", 
    "sgv": 159, 
    "device": "share2", 
    "date": 1453785631000, 
    "_id": "56a7026837663704c846030c", 
    "type": "sgv"
  }, 
  {
    "direction": "Flat", 
    "trend": 4, 
    "dateString": "2016-01-26T05:15:31.000Z", 
    "sgv": 159, 
    "device": "share2", 
    "date": 1453785331000, 
    "_id": "56a7013c37663704c8460304", 
    "type": "sgv"
  }, 
  {
    "direction": "Flat", 
    "trend": 4, 
    "dateString": "2016-01-26T05:10:30.000Z", 
    "sgv": 153, 
    "device": "share2", 
    "date": 1453785030000, 
    "_id": "56a7001037663704c84602f6", 
    "type": "sgv"
  }, 
  {
    "direction": "Flat", 
    "trend": 4, 
    "dateString": "2016-01-26T05:05:32.000Z", 
    "sgv": 157, 
    "device": "share2", 
    "date": 1453784732000, 
    "_id": "56a6fee437663704c84602eb", 
    "type": "sgv"
  }, 
  {
    "direction": "Flat", 
    "trend": 4, 
    "dateString": "2016-01-26T05:00:31.000Z", 
    "sgv": 156, 
    "device": "share2", 
    "date": 1453784431000, 
    "_id": "56a6fdb837663704c84602e2", 
    "type": "sgv"
  }, 
  {
    "direction": "Flat", 
    "trend": 4, 
    "dateString": "2016-01-26T04:55:32.000Z", 
    "sgv": 152, 
    "device": "share2", 
    "date": 1453784132000, 
    "_id": "56a6fc8b37663704c84602d8", 
    "type": "sgv"
  }, 
  {
    "direction": "Flat", 
    "trend": 4, 
    "dateString": "2016-01-26T04:50:30.000Z", 
    "sgv": 151, 
    "device": "share2", 
    "date": 1453783830000, 
    "_id": "56a6fb5f37663704c84602cd", 
    "type": "sgv"
  }
]