{
  "device": "openaps://raspberrypi", 
  "pump": {
    "battery": {
      "status": "normal", 
      "voltage": 1.52
    }, 
    "status": {
      "status": "normal", 
      "timestamp": "2016-01-30T07:53:13.000Z", 
      "bolusing": false, 
      "suspended": false
    }, 
    "reservoir": 250.4, 
    "clock": "2016-01-29T23:51:08-08:00"
  }, 
  "openaps": {
    "suggested": {
      "bg": 104, 
      "temp": "absolute", 
      "snoozeBG": 106, 
      "timestamp": "2016-01-30T07:50:45.000Z", 
      "rate": 0, 
      "reason": "Eventual BG 106>95 but Delta -1 < Exp. Delta 1.2; cancel", 
      "eventualBG": 106, 
      "duration": 0, 
      "mealAssist": "Off: Carbs: 0 Boluses: 0 Target: 105 Deviation: -1 BGI: 1.18", 
      "tick": -1
    }, 
    "iob": {
      "timestamp": "2016-01-30T07:50:45.000Z", 
      "bolussnooze": 0, 
      "basaliob": -0.138, 
      "iob": -0.138, 
      "activity": -0.0094
    }, 
    "enacted": {
      "bg": 104, 
      "temp": "absolute", 
      "snoozeBG": 106, 
      "recieved": true, 
      "reason": "Eventual BG 106>95 but Delta -1 < Exp. Delta 1.2; cancel", 
      "rate": 0, 
      "eventualBG": 106, 
      "timestamp": "2016-01-30T07:51:03.000Z", 
      "duration": 0, 
      "mealAssist": "Off: Carbs: 0 Boluses: 0 Target: 105 Deviation: -1 BGI: 1.18", 
      "tick": -1
    }
  }
}