{
  "device": "openaps://raspberrypi", 
  "pump": {
    "battery": {
      "status": "normal", 
      "voltage": 1.55
    }, 
    "status": {
      "status": "normal", 
      "timestamp": "2016-01-30T08:32:51.000Z", 
      "bolusing": false, 
      "suspended": false
    }, 
    "reservoir": 249.9, 
    "clock": "2016-01-30T00:31:09-08:00"
  }, 
  "openaps": {
    "suggested": {
      "bg": 96, 
      "temp": "absolute", 
      "snoozeBG": 99, 
      "timestamp": "2016-01-30T08:30:48.000Z", 
      "rate": 0, 
      "reason": "Eventual BG 99>95 but Delta -1 < Exp. Delta 0.6; cancel", 
      "eventualBG": 99, 
      "duration": 0, 
      "mealAssist": "Off: Carbs: 0 Boluses: 0 Target: 105 Deviation: -7 BGI: 0.45", 
      "tick": -1
    }, 
    "iob": {
      "timestamp": "2016-01-30T08:30:47.000Z", 
      "bolussnooze": 0, 
      "basaliob": -0.407, 
      "iob": -0.407, 
      "activity": -0.0036
    }, 
    "enacted": {
      "bg": 96, 
      "temp": "absolute", 
      "snoozeBG": 99, 
      "recieved": true, 
      "reason": "Eventual BG 99>95 but Delta -1 < Exp. Delta 0.6; cancel", 
      "rate": 0, 
      "eventualBG": 99, 
      "timestamp": "2016-01-30T08:31:06.000Z", 
      "duration": 0, 
      "mealAssist": "Off: Carbs: 0 Boluses: 0 Target: 105 Deviation: -7 BGI: 0.45", 
      "tick": -1
    }
  }
}