{
  "device": "openaps://raspberrypi", 
  "pump": {
    "battery": {
      "status": "normal", 
      "voltage": 1.55
    }, 
    "status": {
      "status": "normal", 
      "timestamp": "2016-02-02T14:23:03.000Z", 
      "bolusing": false, 
      "suspended": false
    }, 
    "reservoir": 7.3, 
    "clock": "2016-02-02T06:21:07-08:00"
  }, 
  "openaps": {
    "suggested": {
      "bg": 131, 
      "temp": "absolute", 
      "snoozeBG": 93, 
      "timestamp": "2016-02-02T14:20:39.000Z", 
      "rate": 0, 
      "reason": "Eventual BG 93<95, setting -0.77U/hr", 
      "eventualBG": 93, 
      "duration": 30, 
      "mealAssist": "Off: Carbs: 0 Boluses: 0 Target: 105 Deviation: -2 BGI: -1.96", 
      "tick": -2
    }, 
    "iob": {
      "timestamp": "2016-02-02T14:20:38.000Z", 
      "bolussnooze": 0, 
      "basaliob": 1.43, 
      "iob": 1.43, 
      "activity": 0.0157
    }, 
    "enacted": {
      "bg": 131, 
      "temp": "absolute", 
      "snoozeBG": 93, 
      "recieved": true, 
      "reason": "Eventual BG 93<95, setting -0.77U/hr", 
      "rate": 0, 
      "eventualBG": 93, 
      "timestamp": "2016-02-02T14:20:58.000Z", 
      "duration": 30, 
      "mealAssist": "Off: Carbs: 0 Boluses: 0 Target: 105 Deviation: -2 BGI: -1.96", 
      "tick": -2
    }
  }
}