{
  "device": "openaps://murseless", 
  "pump": {
    "battery": {
      "status": "normal", 
      "voltage": 1.56
    }, 
    "status": {
      "status": "normal", 
      "timestamp": "2016-02-12T23:41:52.000Z", 
      "bolusing": false, 
      "suspended": false
    }, 
    "reservoir": 15.7, 
    "clock": "2016-02-12T15:39:43-08:00"
  }, 
  "openaps": {
    "suggested": {
      "bg": 129, 
      "temp": "absolute", 
      "snoozeBG": 101, 
      "timestamp": "2016-02-12T23:42:12.000Z", 
      "rate": 0, 
      "reason": "100 is in range. No temp required; cancel", 
      "eventualBG": 100, 
      "duration": 0, 
      "mealAssist": "Off: Carbs: 31 Boluses: 3.3 Target: 97.5 Deviation: 8 BGI: -3.16", 
      "tick": -2
    }, 
    "iob": {
      "timestamp": "2016-02-12T23:42:11.000Z", 
      "bolussnooze": 0.018, 
      "basaliob": 0.1, 
      "iob": 1.483, 
      "activity": 0.0253
    }, 
    "enacted": {
      "requested": {
        "duration": 0, 
        "rate": 0, 
        "temp": "absolute"
      }, 
      "bg": 129, 
      "temp": "absolute", 
      "snoozeBG": 101, 
      "timestamp": "2016-02-12T23:42:24.000Z", 
      "reason": "100 is in range. No temp required; cancel", 
      "rate": 0, 
      "eventualBG": 100, 
      "recieved": false, 
      "duration": 0, 
      "mealAssist": "Off: Carbs: 31 Boluses: 3.3 Target: 97.5 Deviation: 8 BGI: -3.16", 
      "tick": -2
    }
  }
}